[
  {
    "catalog_id": "0", 
    "content_description_setting": "{\"product_title\":\"1\",\"image\":\"0\",\"guest_notification\":\"0\",\"cancellation_policy\":\"1\",\"short_desc\":\"0\",\"long_desc\":\"0\",\"highlights\":\"0\"}", 
    "created_at": "2024-12-31 05:36:10", 
    "deleted": "0", 
    "is_pos_list": "0", 
    "is_suspended": "0", 
    "last_modified_at": "2024-12-31 05:37:04", 
    "market_merchant_id": "2", 
    "merchant_admin_id": "0", 
    "product_verify_status": "0", 
    "publish_catalog": "1", 
    "template_id": "1313", 
    "template_level_tickets_id": "512632", 
    "ticket_id": "1559498"
  }, 
  {
    "catalog_id": "0", 
    "content_description_setting": "{\"product_title\":\"1\",\"image\":\"0\",\"guest_notification\":\"0\",\"cancellation_policy\":\"1\",\"short_desc\":\"0\",\"long_desc\":\"0\",\"highlights\":\"0\"}", 
    "created_at": "2024-11-26 07:49:02", 
    "deleted": "0", 
    "is_pos_list": "1", 
    "is_suspended": "0", 
    "last_modified_at": "2024-12-26 06:41:40", 
    "market_merchant_id": "1", 
    "merchant_admin_id": "1247", 
    "product_verify_status": "0", 
    "publish_catalog": "1", 
    "template_id": "1170", 
    "template_level_tickets_id": "512324", 
    "ticket_id": "1559260"
  }, 
  {
    "catalog_id": "0", 
    "content_description_setting": "{\"product_title\":\"1\",\"image\":\"0\",\"guest_notification\":\"0\",\"cancellation_policy\":\"1\",\"short_desc\":\"0\",\"long_desc\":\"0\",\"highlights\":\"0\"}", 
    "created_at": "2023-03-09 10:37:34", 
    "deleted": "0", 
    "is_pos_list": "1", 
    "is_suspended": "0", 
    "last_modified_at": "2024-12-25 08:02:08", 
    "market_merchant_id": "1", 
    "merchant_admin_id": "1370", 
    "product_verify_status": "0", 
    "publish_catalog": "1", 
    "template_id": "1480", 
    "template_level_tickets_id": "506337", 
    "ticket_id": "1554162"
  }, 
  {
    "catalog_id": "0", 
    "content_description_setting": "{\"product_title\":\"1\",\"image\":\"0\",\"guest_notification\":\"0\",\"cancellation_policy\":\"1\",\"short_desc\":\"0\",\"long_desc\":\"0\",\"highlights\":\"0\"}", 
    "created_at": "2024-12-31 05:28:16", 
    "deleted": "0", 
    "is_pos_list": "1", 
    "is_suspended": "0", 
    "last_modified_at": "2024-12-31 07:27:01", 
    "market_merchant_id": "1", 
    "merchant_admin_id": "149388", 
    "product_verify_status": "0", 
    "publish_catalog": "1", 
    "template_id": "19279", 
    "template_level_tickets_id": "512630", 
    "ticket_id": "1559496"
  }, 
  {
    "catalog_id": "0", 
    "content_description_setting": "{\"product_title\":\"1\",\"image\":\"0\",\"guest_notification\":\"0\",\"cancellation_policy\":\"1\",\"short_desc\":\"0\",\"long_desc\":\"0\",\"highlights\":\"0\"}", 
    "created_at": "2024-12-30 11:26:24", 
    "deleted": "0", 
    "is_pos_list": "1", 
    "is_suspended": "0", 
    "last_modified_at": "2024-12-30 11:52:29", 
    "market_merchant_id": "1", 
    "merchant_admin_id": "0", 
    "product_verify_status": "0", 
    "publish_catalog": "1", 
    "template_id": "19189", 
    "template_level_tickets_id": "512624", 
    "ticket_id": "1559491"
  }, 
  {
    "catalog_id": "0", 
    "content_description_setting": "{\"product_title\":\"1\",\"image\":\"0\",\"guest_notification\":\"0\",\"cancellation_policy\":\"1\",\"short_desc\":\"0\",\"long_desc\":\"0\",\"highlights\":\"0\"}", 
    "created_at": "2024-12-24 08:28:47", 
    "deleted": "0", 
    "is_pos_list": "1", 
    "is_suspended": "0", 
    "last_modified_at": "2024-12-24 10:40:09", 
    "market_merchant_id": "1", 
    "merchant_admin_id": "148456", 
    "product_verify_status": "0", 
    "publish_catalog": "1", 
    "template_id": "17734", 
    "template_level_tickets_id": "512592", 
    "ticket_id": "1559468"
  }, 
  {
    "catalog_id": "0", 
    "content_description_setting": "{\"product_title\":\"1\",\"image\":\"0\",\"guest_notification\":\"0\",\"cancellation_policy\":\"1\",\"short_desc\":\"0\",\"long_desc\":\"0\",\"highlights\":\"0\"}", 
    "created_at": "2024-12-31 06:01:33", 
    "deleted": "0", 
    "is_pos_list": "1", 
    "is_suspended": "0", 
    "last_modified_at": "2024-12-31 07:27:27", 
    "market_merchant_id": "1", 
    "merchant_admin_id": "149388", 
    "product_verify_status": "0", 
    "publish_catalog": "1", 
    "template_id": "19279", 
    "template_level_tickets_id": "512636", 
    "ticket_id": "1559501"
  }, 
  {
    "catalog_id": "0", 
    "content_description_setting": "{\"product_title\":\"1\",\"image\":\"0\",\"guest_notification\":\"0\",\"cancellation_policy\":\"1\",\"short_desc\":\"0\",\"long_desc\":\"0\",\"highlights\":\"0\"}", 
    "created_at": "2024-12-24 07:17:30", 
    "deleted": "0", 
    "is_pos_list": "1", 
    "is_suspended": "0", 
    "last_modified_at": "2024-12-24 07:21:34", 
    "market_merchant_id": "1", 
    "merchant_admin_id": "149312", 
    "product_verify_status": "0", 
    "publish_catalog": "1", 
    "template_id": "19136", 
    "template_level_tickets_id": "512589", 
    "ticket_id": "1559464"
  }, 
  {
    "catalog_id": "0", 
    "content_description_setting": null, 
    "created_at": "2024-12-24 11:37:19", 
    "deleted": "0", 
    "is_pos_list": "1", 
    "is_suspended": "0", 
    "last_modified_at": "2024-12-24 12:43:04", 
    "market_merchant_id": "1", 
    "merchant_admin_id": "0", 
    "product_verify_status": "0", 
    "publish_catalog": "1", 
    "template_id": "18413", 
    "template_level_tickets_id": "512597", 
    "ticket_id": "1559474"
  }, 
  {
    "catalog_id": "0", 
    "content_description_setting": "{\"product_title\":\"1\",\"image\":\"0\",\"guest_notification\":\"0\",\"cancellation_policy\":\"1\",\"short_desc\":\"0\",\"long_desc\":\"0\",\"highlights\":\"0\"}", 
    "created_at": "2024-12-30 13:24:57", 
    "deleted": "0", 
    "is_pos_list": "0", 
    "is_suspended": "0", 
    "last_modified_at": "2024-12-30 13:24:57", 
    "market_merchant_id": "1", 
    "merchant_admin_id": "0", 
    "product_verify_status": "0", 
    "publish_catalog": "0", 
    "template_id": "19277", 
    "template_level_tickets_id": "512628", 
    "ticket_id": "1559494"
  }, 
  {
    "catalog_id": "0", 
    "content_description_setting": "{\"product_title\":\"1\",\"image\":\"0\",\"guest_notification\":\"0\",\"cancellation_policy\":\"1\",\"short_desc\":\"0\",\"long_desc\":\"0\",\"highlights\":\"0\"}", 
    "created_at": "2024-12-24 10:35:51", 
    "deleted": "0", 
    "is_pos_list": "1", 
    "is_suspended": "0", 
    "last_modified_at": "2024-12-24 10:36:27", 
    "market_merchant_id": "1", 
    "merchant_admin_id": "148456", 
    "product_verify_status": "0", 
    "publish_catalog": "1", 
    "template_id": "17734", 
    "template_level_tickets_id": "512595", 
    "ticket_id": "1559473"
  }, 
  {
    "catalog_id": "0", 
    "content_description_setting": "{\"product_title\":\"1\",\"image\":\"0\",\"guest_notification\":\"0\",\"cancellation_policy\":\"1\",\"short_desc\":\"0\",\"long_desc\":\"0\",\"highlights\":\"0\"}", 
    "created_at": "2025-01-03 05:49:30", 
    "deleted": "0", 
    "is_pos_list": "1", 
    "is_suspended": "0", 
    "last_modified_at": "2025-01-03 05:56:10", 
    "market_merchant_id": "1", 
    "merchant_admin_id": "0", 
    "product_verify_status": "0", 
    "publish_catalog": "1", 
    "template_id": "19189", 
    "template_level_tickets_id": "512657", 
    "ticket_id": "1559519"
  }, 
  {
    "catalog_id": "0", 
    "content_description_setting": "{\"product_title\":\"1\",\"image\":\"0\",\"guest_notification\":\"0\",\"cancellation_policy\":\"1\",\"short_desc\":\"0\",\"long_desc\":\"0\",\"highlights\":\"0\"}", 
    "created_at": "2025-01-02 12:09:56", 
    "deleted": "0", 
    "is_pos_list": "1", 
    "is_suspended": "0", 
    "last_modified_at": "2025-01-02 12:10:58", 
    "market_merchant_id": "1", 
    "merchant_admin_id": "0", 
    "product_verify_status": "0", 
    "publish_catalog": "1", 
    "template_id": "1170", 
    "template_level_tickets_id": "512654", 
    "ticket_id": "1559518"
  }, 
  {
    "catalog_id": "0", 
    "content_description_setting": "{\"product_title\":\"1\",\"image\":\"0\",\"guest_notification\":\"0\",\"cancellation_policy\":\"1\",\"short_desc\":\"0\",\"long_desc\":\"0\",\"highlights\":\"0\"}", 
    "created_at": "2025-01-03 07:23:09", 
    "deleted": "0", 
    "is_pos_list": "1", 
    "is_suspended": "0", 
    "last_modified_at": "2025-01-03 07:33:14", 
    "market_merchant_id": "1", 
    "merchant_admin_id": "0", 
    "product_verify_status": "0", 
    "publish_catalog": "1", 
    "template_id": "19277", 
    "template_level_tickets_id": "512658", 
    "ticket_id": "1559520"
  }, 
  {
    "catalog_id": "0", 
    "content_description_setting": "{\"product_title\":\"1\",\"image\":\"0\",\"guest_notification\":\"0\",\"cancellation_policy\":\"1\",\"short_desc\":\"0\",\"long_desc\":\"0\",\"highlights\":\"0\"}", 
    "created_at": "2024-12-31 06:06:43", 
    "deleted": "0", 
    "is_pos_list": "0", 
    "is_suspended": "0", 
    "last_modified_at": "2024-12-31 06:06:43", 
    "market_merchant_id": "1", 
    "merchant_admin_id": "0", 
    "product_verify_status": "0", 
    "publish_catalog": "0", 
    "template_id": "19279", 
    "template_level_tickets_id": "512637", 
    "ticket_id": "1559502"
  }, 
  {
    "catalog_id": "0", 
    "content_description_setting": "{\"product_title\":\"1\",\"image\":\"0\",\"guest_notification\":\"0\",\"cancellation_policy\":\"1\",\"short_desc\":\"0\",\"long_desc\":\"0\",\"highlights\":\"0\"}", 
    "created_at": "2025-01-02 07:22:03", 
    "deleted": "0", 
    "is_pos_list": "0", 
    "is_suspended": "0", 
    "last_modified_at": "2025-01-02 07:22:03", 
    "market_merchant_id": "1", 
    "merchant_admin_id": "0", 
    "product_verify_status": "0", 
    "publish_catalog": "0", 
    "template_id": "1170", 
    "template_level_tickets_id": "512647", 
    "ticket_id": "1559512"
  }, 
  {
    "catalog_id": "0", 
    "content_description_setting": "{\"product_title\":\"1\",\"image\":\"0\",\"guest_notification\":\"0\",\"cancellation_policy\":\"1\",\"short_desc\":\"0\",\"long_desc\":\"0\",\"highlights\":\"0\"}", 
    "created_at": "2024-12-31 05:37:05", 
    "deleted": "0", 
    "is_pos_list": "0", 
    "is_suspended": "0", 
    "last_modified_at": "2024-12-31 05:37:05", 
    "market_merchant_id": "2", 
    "merchant_admin_id": "0", 
    "product_verify_status": "0", 
    "publish_catalog": "1", 
    "template_id": "1520", 
    "template_level_tickets_id": "512633", 
    "ticket_id": "1559498"
  }, 
  {
    "catalog_id": "0", 
    "content_description_setting": null, 
    "created_at": "2024-12-24 06:25:52", 
    "deleted": "0", 
    "is_pos_list": "0", 
    "is_suspended": "0", 
    "last_modified_at": "2024-12-24 06:25:56", 
    "market_merchant_id": "1", 
    "merchant_admin_id": "0", 
    "product_verify_status": "0", 
    "publish_catalog": "1", 
    "template_id": "18413", 
    "template_level_tickets_id": "512586", 
    "ticket_id": "1559461"
  }, 
  {
    "catalog_id": "0", 
    "content_description_setting": "{\"product_title\":\"1\",\"image\":\"0\",\"guest_notification\":\"0\",\"cancellation_policy\":\"1\",\"short_desc\":\"0\",\"long_desc\":\"0\",\"highlights\":\"0\"}", 
    "created_at": "2024-12-25 08:26:39", 
    "deleted": "0", 
    "is_pos_list": "0", 
    "is_suspended": "0", 
    "last_modified_at": "2024-12-25 09:45:04", 
    "market_merchant_id": "1", 
    "merchant_admin_id": "0", 
    "product_verify_status": "0", 
    "publish_catalog": "1", 
    "template_id": "1349", 
    "template_level_tickets_id": "512606", 
    "ticket_id": "1559480"
  }, 
  {
    "catalog_id": "0", 
    "content_description_setting": "{\"product_title\":\"1\",\"image\":\"0\",\"guest_notification\":\"0\",\"cancellation_policy\":\"1\",\"short_desc\":\"0\",\"long_desc\":\"0\",\"highlights\":\"0\"}", 
    "created_at": "2024-12-25 12:47:57", 
    "deleted": "0", 
    "is_pos_list": "1", 
    "is_suspended": "0", 
    "last_modified_at": "2024-12-25 12:53:20", 
    "market_merchant_id": "1", 
    "merchant_admin_id": "0", 
    "product_verify_status": "0", 
    "publish_catalog": "1", 
    "template_id": "19277", 
    "template_level_tickets_id": "512612", 
    "ticket_id": "1559483"
  }, 
  {
    "catalog_id": "0", 
    "content_description_setting": "{\"product_title\":\"1\",\"image\":\"0\",\"guest_notification\":\"0\",\"cancellation_policy\":\"1\",\"short_desc\":\"0\",\"long_desc\":\"0\",\"highlights\":\"0\"}", 
    "created_at": "2024-12-30 12:24:53", 
    "deleted": "0", 
    "is_pos_list": "1", 
    "is_suspended": "0", 
    "last_modified_at": "2024-12-30 12:24:53", 
    "market_merchant_id": "1", 
    "merchant_admin_id": "1247", 
    "product_verify_status": "0", 
    "publish_catalog": "1", 
    "template_id": "1480", 
    "template_level_tickets_id": "512627", 
    "ticket_id": "1554782"
  }, 
  {
    "catalog_id": "0", 
    "content_description_setting": "{\"product_title\":\"1\",\"image\":\"0\",\"guest_notification\":\"0\",\"cancellation_policy\":\"1\",\"short_desc\":\"0\",\"long_desc\":\"0\",\"highlights\":\"0\"}", 
    "created_at": "2024-12-23 07:23:10", 
    "deleted": "0", 
    "is_pos_list": "1", 
    "is_suspended": "0", 
    "last_modified_at": "2024-12-23 07:28:28", 
    "market_merchant_id": "1", 
    "merchant_admin_id": "148456", 
    "product_verify_status": "0", 
    "publish_catalog": "1", 
    "template_id": "17734", 
    "template_level_tickets_id": "512572", 
    "ticket_id": "1559450"
  }, 
  {
    "catalog_id": "0", 
    "content_description_setting": "{\"product_title\":\"1\",\"image\":\"0\",\"guest_notification\":\"0\",\"cancellation_policy\":\"1\",\"short_desc\":\"0\",\"long_desc\":\"0\",\"highlights\":\"0\"}", 
    "created_at": "2024-12-25 08:23:17", 
    "deleted": "0", 
    "is_pos_list": "1", 
    "is_suspended": "0", 
    "last_modified_at": "2024-12-25 09:45:28", 
    "market_merchant_id": "1", 
    "merchant_admin_id": "0", 
    "product_verify_status": "0", 
    "publish_catalog": "1", 
    "template_id": "1170", 
    "template_level_tickets_id": "512604", 
    "ticket_id": "1559479"
  }, 
  {
    "catalog_id": "0", 
    "content_description_setting": null, 
    "created_at": "2024-12-24 06:25:52", 
    "deleted": "0", 
    "is_pos_list": "0", 
    "is_suspended": "0", 
    "last_modified_at": "2024-12-24 06:25:56", 
    "market_merchant_id": "1", 
    "merchant_admin_id": "0", 
    "product_verify_status": "0", 
    "publish_catalog": "1", 
    "template_id": "18413", 
    "template_level_tickets_id": "512585", 
    "ticket_id": "1559460"
  }, 
  {
    "catalog_id": "0", 
    "content_description_setting": "{\"product_title\":\"1\",\"image\":\"0\",\"guest_notification\":\"0\",\"cancellation_policy\":\"1\",\"short_desc\":\"0\",\"long_desc\":\"0\",\"highlights\":\"0\"}", 
    "created_at": "2024-12-31 07:00:33", 
    "deleted": "0", 
    "is_pos_list": "1", 
    "is_suspended": "0", 
    "last_modified_at": "2024-12-31 07:28:34", 
    "market_merchant_id": "1", 
    "merchant_admin_id": "149388", 
    "product_verify_status": "0", 
    "publish_catalog": "1", 
    "template_id": "19279", 
    "template_level_tickets_id": "512645", 
    "ticket_id": "1559510"
  }, 
  {
    "catalog_id": "0", 
    "content_description_setting": "{\"product_title\":\"1\",\"image\":\"0\",\"guest_notification\":\"0\",\"cancellation_policy\":\"1\",\"short_desc\":\"0\",\"long_desc\":\"0\",\"highlights\":\"0\"}", 
    "created_at": "2025-01-02 11:53:13", 
    "deleted": "0", 
    "is_pos_list": "1", 
    "is_suspended": "0", 
    "last_modified_at": "2025-01-02 11:54:23", 
    "market_merchant_id": "1", 
    "merchant_admin_id": "0", 
    "product_verify_status": "0", 
    "publish_catalog": "1", 
    "template_id": "1349", 
    "template_level_tickets_id": "512651", 
    "ticket_id": "1559517"
  }, 
  {
    "catalog_id": "0", 
    "content_description_setting": "{\"product_title\":\"1\",\"image\":\"0\",\"guest_notification\":\"0\",\"cancellation_policy\":\"1\",\"short_desc\":\"0\",\"long_desc\":\"0\",\"highlights\":\"0\"}", 
    "created_at": "2025-01-02 11:50:22", 
    "deleted": "0", 
    "is_pos_list": "1", 
    "is_suspended": "0", 
    "last_modified_at": "2025-01-02 11:53:57", 
    "market_merchant_id": "1", 
    "merchant_admin_id": "0", 
    "product_verify_status": "0", 
    "publish_catalog": "1", 
    "template_id": "1170", 
    "template_level_tickets_id": "512649", 
    "ticket_id": "1559517"
  }, 
  {
    "catalog_id": "0", 
    "content_description_setting": "{\"product_title\":\"1\",\"image\":\"0\",\"guest_notification\":\"0\",\"cancellation_policy\":\"1\",\"short_desc\":\"0\",\"long_desc\":\"0\",\"highlights\":\"0\"}", 
    "created_at": "2024-12-30 11:25:37", 
    "deleted": "0", 
    "is_pos_list": "1", 
    "is_suspended": "0", 
    "last_modified_at": "2024-12-30 11:54:10", 
    "market_merchant_id": "1", 
    "merchant_admin_id": "0", 
    "product_verify_status": "0", 
    "publish_catalog": "1", 
    "template_id": "19189", 
    "template_level_tickets_id": "512623", 
    "ticket_id": "1559490"
  }, 
  {
    "catalog_id": "0", 
    "content_description_setting": "{\"product_title\":\"1\",\"image\":\"0\",\"guest_notification\":\"0\",\"cancellation_policy\":\"1\",\"short_desc\":\"0\",\"long_desc\":\"0\",\"highlights\":\"0\"}", 
    "created_at": "2024-12-30 12:04:31", 
    "deleted": "0", 
    "is_pos_list": "1", 
    "is_suspended": "0", 
    "last_modified_at": "2024-12-30 12:07:57", 
    "market_merchant_id": "1", 
    "merchant_admin_id": "0", 
    "product_verify_status": "0", 
    "publish_catalog": "1", 
    "template_id": "19189", 
    "template_level_tickets_id": "512626", 
    "ticket_id": "1559493"
  }, 
  {
    "catalog_id": "0", 
    "content_description_setting": "{\"product_title\":\"1\",\"image\":\"0\",\"guest_notification\":\"0\",\"cancellation_policy\":\"1\",\"short_desc\":\"0\",\"long_desc\":\"0\",\"highlights\":\"0\"}", 
    "created_at": "2024-12-23 08:22:43", 
    "deleted": "0", 
    "is_pos_list": "0", 
    "is_suspended": "0", 
    "last_modified_at": "2024-12-23 08:22:43", 
    "market_merchant_id": "1", 
    "merchant_admin_id": "0", 
    "product_verify_status": "0", 
    "publish_catalog": "1", 
    "template_id": "1675", 
    "template_level_tickets_id": "512575", 
    "ticket_id": "1558680"
  }, 
  {
    "catalog_id": "0", 
    "content_description_setting": "{\"product_title\":\"1\",\"image\":\"0\",\"guest_notification\":\"0\",\"cancellation_policy\":\"1\",\"short_desc\":\"0\",\"long_desc\":\"0\",\"highlights\":\"0\"}", 
    "created_at": "2025-01-02 12:10:36", 
    "deleted": "0", 
    "is_pos_list": "1", 
    "is_suspended": "0", 
    "last_modified_at": "2025-01-02 12:11:51", 
    "market_merchant_id": "1", 
    "merchant_admin_id": "0", 
    "product_verify_status": "0", 
    "publish_catalog": "1", 
    "template_id": "1349", 
    "template_level_tickets_id": "512655", 
    "ticket_id": "1559518"
  }, 
  {
    "catalog_id": "0", 
    "content_description_setting": "{\"product_title\":\"1\",\"image\":\"0\",\"guest_notification\":\"0\",\"cancellation_policy\":\"1\",\"short_desc\":\"0\",\"long_desc\":\"0\",\"highlights\":\"0\"}", 
    "created_at": "2024-12-26 10:09:44", 
    "deleted": "0", 
    "is_pos_list": "1", 
    "is_suspended": "0", 
    "last_modified_at": "2024-12-26 10:16:11", 
    "market_merchant_id": "1", 
    "merchant_admin_id": "0", 
    "product_verify_status": "0", 
    "publish_catalog": "1", 
    "template_id": "19189", 
    "template_level_tickets_id": "512615", 
    "ticket_id": "1559485"
  }, 
  {
    "catalog_id": "0", 
    "content_description_setting": "{\"product_title\":\"1\",\"image\":\"0\",\"guest_notification\":\"0\",\"cancellation_policy\":\"1\",\"short_desc\":\"0\",\"long_desc\":\"0\",\"highlights\":\"0\"}", 
    "created_at": "2024-12-23 13:16:30", 
    "deleted": "0", 
    "is_pos_list": "0", 
    "is_suspended": "0", 
    "last_modified_at": "2024-12-23 13:16:30", 
    "market_merchant_id": "1", 
    "merchant_admin_id": "0", 
    "product_verify_status": "0", 
    "publish_catalog": "0", 
    "template_id": "18413", 
    "template_level_tickets_id": "512581", 
    "ticket_id": "1559458"
  }, 
  {
    "catalog_id": "0", 
    "content_description_setting": "{\"product_title\":\"1\",\"image\":\"0\",\"guest_notification\":\"0\",\"cancellation_policy\":\"1\",\"short_desc\":\"0\",\"long_desc\":\"0\",\"highlights\":\"0\"}", 
    "created_at": "2024-12-23 13:24:31", 
    "deleted": "0", 
    "is_pos_list": "0", 
    "is_suspended": "0", 
    "last_modified_at": "2024-12-23 13:24:31", 
    "market_merchant_id": "1", 
    "merchant_admin_id": "148964", 
    "product_verify_status": "0", 
    "publish_catalog": "1", 
    "template_id": "1342", 
    "template_level_tickets_id": "512582", 
    "ticket_id": "1559458"
  }, 
  {
    "catalog_id": "0", 
    "content_description_setting": "{\"product_title\":\"1\",\"image\":\"0\",\"guest_notification\":\"0\",\"cancellation_policy\":\"1\",\"short_desc\":\"0\",\"long_desc\":\"0\",\"highlights\":\"0\"}", 
    "created_at": "2024-12-24 04:43:46", 
    "deleted": "0", 
    "is_pos_list": "0", 
    "is_suspended": "0", 
    "last_modified_at": "2024-12-24 04:43:46", 
    "market_merchant_id": "1", 
    "merchant_admin_id": "148964", 
    "product_verify_status": "0", 
    "publish_catalog": "1", 
    "template_id": "1342", 
    "template_level_tickets_id": "512584", 
    "ticket_id": "1559459"
  }, 
  {
    "catalog_id": "0", 
    "content_description_setting": "{\"product_title\":\"1\",\"image\":\"0\",\"guest_notification\":\"0\",\"cancellation_policy\":\"1\",\"short_desc\":\"0\",\"long_desc\":\"0\",\"highlights\":\"0\"}", 
    "created_at": "2024-12-25 09:50:03", 
    "deleted": "0", 
    "is_pos_list": "1", 
    "is_suspended": "0", 
    "last_modified_at": "2024-12-25 09:50:03", 
    "market_merchant_id": "1", 
    "merchant_admin_id": "1247", 
    "product_verify_status": "0", 
    "publish_catalog": "1", 
    "template_id": "1342", 
    "template_level_tickets_id": "512609", 
    "ticket_id": "1559480"
  }, 
  {
    "catalog_id": "0", 
    "content_description_setting": "{\"product_title\":\"1\",\"image\":\"0\",\"guest_notification\":\"0\",\"cancellation_policy\":\"1\",\"short_desc\":\"0\",\"long_desc\":\"0\",\"highlights\":\"0\"}", 
    "created_at": "2025-01-02 07:44:34", 
    "deleted": "0", 
    "is_pos_list": "1", 
    "is_suspended": "0", 
    "last_modified_at": "2025-01-02 10:20:43", 
    "market_merchant_id": "1", 
    "merchant_admin_id": "1247", 
    "product_verify_status": "0", 
    "publish_catalog": "1", 
    "template_id": "1750", 
    "template_level_tickets_id": "512648", 
    "ticket_id": "1559512"
  }, 
  {
    "catalog_id": "0", 
    "content_description_setting": "{\"product_title\":\"1\",\"image\":\"0\",\"guest_notification\":\"0\",\"cancellation_policy\":\"1\",\"short_desc\":\"0\",\"long_desc\":\"0\",\"highlights\":\"0\"}", 
    "created_at": "2023-04-12 11:33:27", 
    "deleted": "0", 
    "is_pos_list": "0", 
    "is_suspended": "0", 
    "last_modified_at": "2025-01-03 07:25:55", 
    "market_merchant_id": "1", 
    "merchant_admin_id": "0", 
    "product_verify_status": "0", 
    "publish_catalog": "1", 
    "template_id": "1342", 
    "template_level_tickets_id": "506842", 
    "ticket_id": "1554780"
  }, 
  {
    "catalog_id": "0", 
    "content_description_setting": null, 
    "created_at": "2024-12-24 11:37:19", 
    "deleted": "0", 
    "is_pos_list": "0", 
    "is_suspended": "0", 
    "last_modified_at": "2024-12-24 11:37:21", 
    "market_merchant_id": "1", 
    "merchant_admin_id": "0", 
    "product_verify_status": "0", 
    "publish_catalog": "1", 
    "template_id": "18413", 
    "template_level_tickets_id": "512598", 
    "ticket_id": "1559475"
  }, 
  {
    "catalog_id": "0", 
    "content_description_setting": "{\"product_title\":\"1\",\"image\":\"0\",\"guest_notification\":\"0\",\"cancellation_policy\":\"1\",\"short_desc\":\"0\",\"long_desc\":\"0\",\"highlights\":\"0\"}", 
    "created_at": "2025-01-02 12:11:16", 
    "deleted": "0", 
    "is_pos_list": "1", 
    "is_suspended": "0", 
    "last_modified_at": "2025-01-02 12:11:16", 
    "market_merchant_id": "1", 
    "merchant_admin_id": "469", 
    "product_verify_status": "0", 
    "publish_catalog": "1", 
    "template_id": "19052", 
    "template_level_tickets_id": "512656", 
    "ticket_id": "1559514"
  }, 
  {
    "catalog_id": "0", 
    "content_description_setting": "{\"product_title\":\"1\",\"image\":\"0\",\"guest_notification\":\"0\",\"cancellation_policy\":\"1\",\"short_desc\":\"0\",\"long_desc\":\"0\",\"highlights\":\"0\"}", 
    "created_at": "2024-12-23 07:19:44", 
    "deleted": "0", 
    "is_pos_list": "1", 
    "is_suspended": "0", 
    "last_modified_at": "2024-12-23 07:28:28", 
    "market_merchant_id": "1", 
    "merchant_admin_id": "148456", 
    "product_verify_status": "0", 
    "publish_catalog": "1", 
    "template_id": "17734", 
    "template_level_tickets_id": "512571", 
    "ticket_id": "1559449"
  }, 
  {
    "catalog_id": "0", 
    "content_description_setting": "{\"product_title\":\"1\",\"image\":\"0\",\"guest_notification\":\"0\",\"cancellation_policy\":\"1\",\"short_desc\":\"0\",\"long_desc\":\"0\",\"highlights\":\"0\"}", 
    "created_at": "2024-12-26 07:34:08", 
    "deleted": "0", 
    "is_pos_list": "1", 
    "is_suspended": "0", 
    "last_modified_at": "2024-12-26 07:36:54", 
    "market_merchant_id": "1", 
    "merchant_admin_id": "0", 
    "product_verify_status": "0", 
    "publish_catalog": "1", 
    "template_id": "19277", 
    "template_level_tickets_id": "512614", 
    "ticket_id": "1559484"
  }, 
  {
    "catalog_id": "0", 
    "content_description_setting": "{\"product_title\":\"1\",\"image\":\"0\",\"guest_notification\":\"0\",\"cancellation_policy\":\"1\",\"short_desc\":\"0\",\"long_desc\":\"0\",\"highlights\":\"0\"}", 
    "created_at": "2024-12-25 06:26:37", 
    "deleted": "0", 
    "is_pos_list": "1", 
    "is_suspended": "0", 
    "last_modified_at": "2024-12-25 06:26:37", 
    "market_merchant_id": "1", 
    "merchant_admin_id": "149386", 
    "product_verify_status": "0", 
    "publish_catalog": "1", 
    "template_id": "19276", 
    "template_level_tickets_id": "512602", 
    "ticket_id": "1559476"
  }, 
  {
    "catalog_id": "0", 
    "content_description_setting": "{\"product_title\":\"1\",\"image\":\"0\",\"guest_notification\":\"0\",\"cancellation_policy\":\"1\",\"short_desc\":\"0\",\"long_desc\":\"0\",\"highlights\":\"0\"}", 
    "created_at": "2024-12-31 06:35:37", 
    "deleted": "0", 
    "is_pos_list": "1", 
    "is_suspended": "0", 
    "last_modified_at": "2024-12-31 06:53:39", 
    "market_merchant_id": "1", 
    "merchant_admin_id": "148456", 
    "product_verify_status": "0", 
    "publish_catalog": "1", 
    "template_id": "17734", 
    "template_level_tickets_id": "512638", 
    "ticket_id": "1559503"
  }, 
  {
    "catalog_id": "0", 
    "content_description_setting": null, 
    "created_at": "2024-12-24 06:25:52", 
    "deleted": "0", 
    "is_pos_list": "0", 
    "is_suspended": "0", 
    "last_modified_at": "2024-12-24 06:25:56", 
    "market_merchant_id": "1", 
    "merchant_admin_id": "0", 
    "product_verify_status": "0", 
    "publish_catalog": "1", 
    "template_id": "18413", 
    "template_level_tickets_id": "512587", 
    "ticket_id": "1559462"
  }, 
  {
    "catalog_id": "0", 
    "content_description_setting": "{\"product_title\":\"1\",\"image\":\"0\",\"guest_notification\":\"0\",\"cancellation_policy\":\"1\",\"short_desc\":\"0\",\"long_desc\":\"0\",\"highlights\":\"0\"}", 
    "created_at": "2024-12-31 05:45:18", 
    "deleted": "0", 
    "is_pos_list": "1", 
    "is_suspended": "0", 
    "last_modified_at": "2024-12-31 06:09:37", 
    "market_merchant_id": "1", 
    "merchant_admin_id": "0", 
    "product_verify_status": "0", 
    "publish_catalog": "1", 
    "template_id": "19277", 
    "template_level_tickets_id": "512634", 
    "ticket_id": "1559499"
  }, 
  {
    "catalog_id": "0", 
    "content_description_setting": "{\"product_title\":\"1\",\"image\":\"0\",\"guest_notification\":\"0\",\"cancellation_policy\":\"1\",\"short_desc\":\"0\",\"long_desc\":\"0\",\"highlights\":\"0\"}", 
    "created_at": "2024-12-25 07:58:26", 
    "deleted": "0", 
    "is_pos_list": "1", 
    "is_suspended": "0", 
    "last_modified_at": "2024-12-25 07:58:26", 
    "market_merchant_id": "1", 
    "merchant_admin_id": "148964", 
    "product_verify_status": "0", 
    "publish_catalog": "1", 
    "template_id": "1480", 
    "template_level_tickets_id": "512603", 
    "ticket_id": "1559459"
  }, 
  {
    "catalog_id": "0", 
    "content_description_setting": "{\"product_title\":\"1\",\"image\":\"0\",\"guest_notification\":\"0\",\"cancellation_policy\":\"1\",\"short_desc\":\"0\",\"long_desc\":\"0\",\"highlights\":\"0\"}", 
    "created_at": "2024-12-25 10:32:33", 
    "deleted": "0", 
    "is_pos_list": "1", 
    "is_suspended": "0", 
    "last_modified_at": "2024-12-25 10:33:29", 
    "market_merchant_id": "2", 
    "merchant_admin_id": "1224", 
    "product_verify_status": "0", 
    "publish_catalog": "1", 
    "template_id": "1313", 
    "template_level_tickets_id": "512610", 
    "ticket_id": "1559481"
  }, 
  {
    "catalog_id": "0", 
    "content_description_setting": "{\"product_title\":\"1\",\"image\":\"0\",\"guest_notification\":\"0\",\"cancellation_policy\":\"1\",\"short_desc\":\"0\",\"long_desc\":\"0\",\"highlights\":\"0\"}", 
    "created_at": "2024-12-30 05:51:36", 
    "deleted": "0", 
    "is_pos_list": "1", 
    "is_suspended": "0", 
    "last_modified_at": "2024-12-30 05:51:36", 
    "market_merchant_id": "1", 
    "merchant_admin_id": "1725", 
    "product_verify_status": "0", 
    "publish_catalog": "1", 
    "template_id": "1480", 
    "template_level_tickets_id": "512621", 
    "ticket_id": "158748"
  }, 
  {
    "catalog_id": "0", 
    "content_description_setting": "{\"product_title\":\"1\",\"image\":\"0\",\"guest_notification\":\"0\",\"cancellation_policy\":\"1\",\"short_desc\":\"0\",\"long_desc\":\"0\",\"highlights\":\"0\"}", 
    "created_at": "2024-12-24 08:32:12", 
    "deleted": "0", 
    "is_pos_list": "1", 
    "is_suspended": "0", 
    "last_modified_at": "2024-12-24 10:40:09", 
    "market_merchant_id": "1", 
    "merchant_admin_id": "148456", 
    "product_verify_status": "0", 
    "publish_catalog": "1", 
    "template_id": "17734", 
    "template_level_tickets_id": "512593", 
    "ticket_id": "1559469"
  }, 
  {
    "catalog_id": "0", 
    "content_description_setting": "{\"product_title\":\"1\",\"image\":\"0\",\"guest_notification\":\"0\",\"cancellation_policy\":\"1\",\"short_desc\":\"0\",\"long_desc\":\"0\",\"highlights\":\"0\"}", 
    "created_at": "2024-12-31 06:38:51", 
    "deleted": "0", 
    "is_pos_list": "1", 
    "is_suspended": "0", 
    "last_modified_at": "2024-12-31 06:53:39", 
    "market_merchant_id": "1", 
    "merchant_admin_id": "148456", 
    "product_verify_status": "0", 
    "publish_catalog": "1", 
    "template_id": "17734", 
    "template_level_tickets_id": "512640", 
    "ticket_id": "1559505"
  }, 
  {
    "catalog_id": "0", 
    "content_description_setting": "{\"product_title\":\"1\",\"image\":\"0\",\"guest_notification\":\"0\",\"cancellation_policy\":\"1\",\"short_desc\":\"0\",\"long_desc\":\"0\",\"highlights\":\"0\"}", 
    "created_at": "2025-01-02 11:52:27", 
    "deleted": "0", 
    "is_pos_list": "0", 
    "is_suspended": "0", 
    "last_modified_at": "2025-01-02 11:52:27", 
    "market_merchant_id": "1", 
    "merchant_admin_id": "469", 
    "product_verify_status": "0", 
    "publish_catalog": "1", 
    "template_id": "1342", 
    "template_level_tickets_id": "512650", 
    "ticket_id": "1559514"
  }, 
  {
    "catalog_id": "0", 
    "content_description_setting": "{\"product_title\":\"1\",\"image\":\"0\",\"guest_notification\":\"0\",\"cancellation_policy\":\"1\",\"short_desc\":\"0\",\"long_desc\":\"0\",\"highlights\":\"0\"}", 
    "created_at": "2025-01-02 12:09:33", 
    "deleted": "0", 
    "is_pos_list": "0", 
    "is_suspended": "0", 
    "last_modified_at": "2025-01-02 12:10:02", 
    "market_merchant_id": "1", 
    "merchant_admin_id": "148964", 
    "product_verify_status": "0", 
    "publish_catalog": "1", 
    "template_id": "1750", 
    "template_level_tickets_id": "512653", 
    "ticket_id": "1558829"
  }, 
  {
    "catalog_id": "0", 
    "content_description_setting": null, 
    "created_at": "2024-12-24 06:25:52", 
    "deleted": "0", 
    "is_pos_list": "0", 
    "is_suspended": "0", 
    "last_modified_at": "2024-12-24 06:25:56", 
    "market_merchant_id": "1", 
    "merchant_admin_id": "0", 
    "product_verify_status": "0", 
    "publish_catalog": "1", 
    "template_id": "18413", 
    "template_level_tickets_id": "512588", 
    "ticket_id": "1559463"
  }, 
  {
    "catalog_id": "0", 
    "content_description_setting": "{\"product_title\":\"1\",\"image\":\"0\",\"guest_notification\":\"0\",\"cancellation_policy\":\"1\",\"short_desc\":\"0\",\"long_desc\":\"0\",\"highlights\":\"0\"}", 
    "created_at": "2024-12-25 09:49:16", 
    "deleted": "0", 
    "is_pos_list": "1", 
    "is_suspended": "0", 
    "last_modified_at": "2024-12-25 09:49:16", 
    "market_merchant_id": "1", 
    "merchant_admin_id": "1247", 
    "product_verify_status": "0", 
    "publish_catalog": "1", 
    "template_id": "1342", 
    "template_level_tickets_id": "512608", 
    "ticket_id": "1559479"
  }, 
  {
    "catalog_id": "0", 
    "content_description_setting": "{\"product_title\":\"1\",\"image\":\"0\",\"guest_notification\":\"0\",\"cancellation_policy\":\"1\",\"short_desc\":\"0\",\"long_desc\":\"0\",\"highlights\":\"0\"}", 
    "created_at": "2024-12-31 06:53:37", 
    "deleted": "0", 
    "is_pos_list": "1", 
    "is_suspended": "0", 
    "last_modified_at": "2024-12-31 07:28:25", 
    "market_merchant_id": "1", 
    "merchant_admin_id": "149388", 
    "product_verify_status": "0", 
    "publish_catalog": "1", 
    "template_id": "19279", 
    "template_level_tickets_id": "512644", 
    "ticket_id": "1559509"
  }, 
  {
    "catalog_id": "0", 
    "content_description_setting": "{\"product_title\":\"1\",\"image\":\"0\",\"guest_notification\":\"0\",\"cancellation_policy\":\"1\",\"short_desc\":\"0\",\"long_desc\":\"0\",\"highlights\":\"0\"}", 
    "created_at": "2024-12-24 08:21:48", 
    "deleted": "0", 
    "is_pos_list": "1", 
    "is_suspended": "0", 
    "last_modified_at": "2024-12-24 08:22:25", 
    "market_merchant_id": "1", 
    "merchant_admin_id": "148456", 
    "product_verify_status": "0", 
    "publish_catalog": "1", 
    "template_id": "17734", 
    "template_level_tickets_id": "512591", 
    "ticket_id": "1559467"
  }, 
  {
    "catalog_id": "0", 
    "content_description_setting": null, 
    "created_at": "2024-12-24 11:48:15", 
    "deleted": "0", 
    "is_pos_list": "1", 
    "is_suspended": "0", 
    "last_modified_at": "2024-12-24 11:48:20", 
    "market_merchant_id": "1", 
    "merchant_admin_id": "148964", 
    "product_verify_status": "0", 
    "publish_catalog": "1", 
    "template_id": "1170", 
    "template_level_tickets_id": "512599", 
    "ticket_id": "1559474"
  }, 
  {
    "catalog_id": "0", 
    "content_description_setting": "{\"product_title\":\"1\",\"image\":\"0\",\"guest_notification\":\"0\",\"cancellation_policy\":\"1\",\"short_desc\":\"0\",\"long_desc\":\"0\",\"highlights\":\"0\"}", 
    "created_at": "2024-12-30 05:13:13", 
    "deleted": "0", 
    "is_pos_list": "1", 
    "is_suspended": "0", 
    "last_modified_at": "2024-12-30 05:13:52", 
    "market_merchant_id": "1", 
    "merchant_admin_id": "0", 
    "product_verify_status": "0", 
    "publish_catalog": "1", 
    "template_id": "1349", 
    "template_level_tickets_id": "512620", 
    "ticket_id": "1559488"
  }, 
  {
    "catalog_id": "0", 
    "content_description_setting": "{\"product_title\":\"1\",\"image\":\"0\",\"guest_notification\":\"0\",\"cancellation_policy\":\"1\",\"short_desc\":\"0\",\"long_desc\":\"0\",\"highlights\":\"0\"}", 
    "created_at": "2024-12-23 12:04:01", 
    "deleted": "0", 
    "is_pos_list": "1", 
    "is_suspended": "0", 
    "last_modified_at": "2024-12-23 12:04:45", 
    "market_merchant_id": "1", 
    "merchant_admin_id": "148456", 
    "product_verify_status": "0", 
    "publish_catalog": "1", 
    "template_id": "17734", 
    "template_level_tickets_id": "512579", 
    "ticket_id": "1559456"
  }, 
  {
    "catalog_id": "0", 
    "content_description_setting": "{\"product_title\":\"1\",\"image\":\"0\",\"guest_notification\":\"0\",\"cancellation_policy\":\"1\",\"short_desc\":\"0\",\"long_desc\":\"0\",\"highlights\":\"0\"}", 
    "created_at": "2024-12-23 11:58:26", 
    "deleted": "0", 
    "is_pos_list": "1", 
    "is_suspended": "0", 
    "last_modified_at": "2024-12-23 12:04:45", 
    "market_merchant_id": "1", 
    "merchant_admin_id": "148456", 
    "product_verify_status": "0", 
    "publish_catalog": "1", 
    "template_id": "17734", 
    "template_level_tickets_id": "512578", 
    "ticket_id": "1559455"
  }, 
  {
    "catalog_id": "0", 
    "content_description_setting": "{\"product_title\":\"1\",\"image\":\"0\",\"guest_notification\":\"0\",\"cancellation_policy\":\"1\",\"short_desc\":\"0\",\"long_desc\":\"0\",\"highlights\":\"0\"}", 
    "created_at": "2024-12-25 05:53:39", 
    "deleted": "0", 
    "is_pos_list": "0", 
    "is_suspended": "0", 
    "last_modified_at": "2024-12-25 05:53:39", 
    "market_merchant_id": "1", 
    "merchant_admin_id": "0", 
    "product_verify_status": "0", 
    "publish_catalog": "0", 
    "template_id": "19274", 
    "template_level_tickets_id": "512601", 
    "ticket_id": "1559476"
  }, 
  {
    "catalog_id": "0", 
    "content_description_setting": "{\"product_title\":\"1\",\"image\":\"0\",\"guest_notification\":\"0\",\"cancellation_policy\":\"1\",\"short_desc\":\"0\",\"long_desc\":\"0\",\"highlights\":\"0\"}", 
    "created_at": "2024-12-26 10:12:58", 
    "deleted": "0", 
    "is_pos_list": "1", 
    "is_suspended": "0", 
    "last_modified_at": "2024-12-26 10:16:07", 
    "market_merchant_id": "1", 
    "merchant_admin_id": "0", 
    "product_verify_status": "0", 
    "publish_catalog": "1", 
    "template_id": "19189", 
    "template_level_tickets_id": "512616", 
    "ticket_id": "1559486"
  }, 
  {
    "catalog_id": "0", 
    "content_description_setting": "{\"product_title\":\"1\",\"image\":\"0\",\"guest_notification\":\"0\",\"cancellation_policy\":\"1\",\"short_desc\":\"0\",\"long_desc\":\"0\",\"highlights\":\"0\"}", 
    "created_at": "2024-12-31 05:55:22", 
    "deleted": "0", 
    "is_pos_list": "1", 
    "is_suspended": "0", 
    "last_modified_at": "2024-12-31 07:27:21", 
    "market_merchant_id": "1", 
    "merchant_admin_id": "149388", 
    "product_verify_status": "0", 
    "publish_catalog": "1", 
    "template_id": "19279", 
    "template_level_tickets_id": "512635", 
    "ticket_id": "1559500"
  }, 
  {
    "catalog_id": "0", 
    "content_description_setting": "{\"product_title\":\"1\",\"image\":\"0\",\"guest_notification\":\"0\",\"cancellation_policy\":\"1\",\"short_desc\":\"0\",\"long_desc\":\"0\",\"highlights\":\"0\"}", 
    "created_at": "2024-12-23 11:36:42", 
    "deleted": "0", 
    "is_pos_list": "1", 
    "is_suspended": "0", 
    "last_modified_at": "2024-12-23 11:37:30", 
    "market_merchant_id": "1", 
    "merchant_admin_id": "148456", 
    "product_verify_status": "0", 
    "publish_catalog": "1", 
    "template_id": "17734", 
    "template_level_tickets_id": "512576", 
    "ticket_id": "1559453"
  }, 
  {
    "catalog_id": "0", 
    "content_description_setting": "{\"product_title\":\"1\",\"image\":\"0\",\"guest_notification\":\"0\",\"cancellation_policy\":\"1\",\"short_desc\":\"0\",\"long_desc\":\"0\",\"highlights\":\"0\"}", 
    "created_at": "2024-12-23 07:27:17", 
    "deleted": "0", 
    "is_pos_list": "1", 
    "is_suspended": "0", 
    "last_modified_at": "2024-12-23 07:28:28", 
    "market_merchant_id": "1", 
    "merchant_admin_id": "148456", 
    "product_verify_status": "0", 
    "publish_catalog": "1", 
    "template_id": "17734", 
    "template_level_tickets_id": "512573", 
    "ticket_id": "1559451"
  }, 
  {
    "catalog_id": "0", 
    "content_description_setting": "{\"product_title\":\"1\",\"image\":\"0\",\"guest_notification\":\"0\",\"cancellation_policy\":\"1\",\"short_desc\":\"0\",\"long_desc\":\"0\",\"highlights\":\"0\"}", 
    "created_at": "2024-12-25 11:41:07", 
    "deleted": "0", 
    "is_pos_list": "1", 
    "is_suspended": "0", 
    "last_modified_at": "2024-12-25 12:02:46", 
    "market_merchant_id": "1", 
    "merchant_admin_id": "0", 
    "product_verify_status": "0", 
    "publish_catalog": "1", 
    "template_id": "19277", 
    "template_level_tickets_id": "512611", 
    "ticket_id": "1559482"
  }, 
  {
    "catalog_id": "0", 
    "content_description_setting": "{\"product_title\":\"1\",\"image\":\"0\",\"guest_notification\":\"0\",\"cancellation_policy\":\"1\",\"short_desc\":\"0\",\"long_desc\":\"0\",\"highlights\":\"0\"}", 
    "created_at": "2024-12-27 08:20:35", 
    "deleted": "0", 
    "is_pos_list": "1", 
    "is_suspended": "0", 
    "last_modified_at": "2024-12-27 08:24:39", 
    "market_merchant_id": "1", 
    "merchant_admin_id": "0", 
    "product_verify_status": "0", 
    "publish_catalog": "1", 
    "template_id": "19189", 
    "template_level_tickets_id": "512618", 
    "ticket_id": "1559487"
  }, 
  {
    "catalog_id": "0", 
    "content_description_setting": "{\"product_title\":\"1\",\"image\":\"0\",\"guest_notification\":\"0\",\"cancellation_policy\":\"1\",\"short_desc\":\"0\",\"long_desc\":\"0\",\"highlights\":\"0\"}", 
    "created_at": "2024-12-26 06:45:58", 
    "deleted": "0", 
    "is_pos_list": "1", 
    "is_suspended": "0", 
    "last_modified_at": "2024-12-26 06:45:58", 
    "market_merchant_id": "1", 
    "merchant_admin_id": "148964", 
    "product_verify_status": "0", 
    "publish_catalog": "1", 
    "template_id": "1316", 
    "template_level_tickets_id": "512613", 
    "ticket_id": "1558680"
  }, 
  {
    "catalog_id": "0", 
    "content_description_setting": "{\"product_title\":\"1\",\"image\":\"0\",\"guest_notification\":\"0\",\"cancellation_policy\":\"1\",\"short_desc\":\"0\",\"long_desc\":\"0\",\"highlights\":\"0\"}", 
    "created_at": "2024-12-31 05:34:28", 
    "deleted": "0", 
    "is_pos_list": "1", 
    "is_suspended": "0", 
    "last_modified_at": "2024-12-31 07:27:10", 
    "market_merchant_id": "1", 
    "merchant_admin_id": "149388", 
    "product_verify_status": "0", 
    "publish_catalog": "1", 
    "template_id": "19279", 
    "template_level_tickets_id": "512631", 
    "ticket_id": "1559497"
  }, 
  {
    "catalog_id": "0", 
    "content_description_setting": "{\"product_title\":\"1\",\"image\":\"0\",\"guest_notification\":\"0\",\"cancellation_policy\":\"1\",\"short_desc\":\"0\",\"long_desc\":\"0\",\"highlights\":\"0\"}", 
    "created_at": "2025-01-02 12:09:17", 
    "deleted": "0", 
    "is_pos_list": "1", 
    "is_suspended": "0", 
    "last_modified_at": "2025-01-02 12:09:17", 
    "market_merchant_id": "1", 
    "merchant_admin_id": "469", 
    "product_verify_status": "0", 
    "publish_catalog": "1", 
    "template_id": "1750", 
    "template_level_tickets_id": "512652", 
    "ticket_id": "1559514"
  }, 
  {
    "catalog_id": "0", 
    "content_description_setting": "{\"product_title\":\"1\",\"image\":\"0\",\"guest_notification\":\"0\",\"cancellation_policy\":\"1\",\"short_desc\":\"0\",\"long_desc\":\"0\",\"highlights\":\"0\"}", 
    "created_at": "2024-12-27 05:38:42", 
    "deleted": "0", 
    "is_pos_list": "1", 
    "is_suspended": "0", 
    "last_modified_at": "2024-12-27 05:38:42", 
    "market_merchant_id": "1", 
    "merchant_admin_id": "1725", 
    "product_verify_status": "0", 
    "publish_catalog": "1", 
    "template_id": "1170", 
    "template_level_tickets_id": "512617", 
    "ticket_id": "158748"
  }, 
  {
    "catalog_id": "0", 
    "content_description_setting": "{\"product_title\":\"1\",\"image\":\"0\",\"guest_notification\":\"0\",\"cancellation_policy\":\"1\",\"short_desc\":\"0\",\"long_desc\":\"0\",\"highlights\":\"0\"}", 
    "created_at": "2024-12-31 06:46:38", 
    "deleted": "0", 
    "is_pos_list": "1", 
    "is_suspended": "0", 
    "last_modified_at": "2024-12-31 06:53:39", 
    "market_merchant_id": "1", 
    "merchant_admin_id": "148456", 
    "product_verify_status": "0", 
    "publish_catalog": "1", 
    "template_id": "17734", 
    "template_level_tickets_id": "512643", 
    "ticket_id": "1559507"
  }, 
  {
    "catalog_id": "0", 
    "content_description_setting": null, 
    "created_at": "2024-12-24 12:25:54", 
    "deleted": "0", 
    "is_pos_list": "1", 
    "is_suspended": "0", 
    "last_modified_at": "2024-12-24 12:25:54", 
    "market_merchant_id": "1", 
    "merchant_admin_id": "148964", 
    "product_verify_status": "0", 
    "publish_catalog": "1", 
    "template_id": "1170", 
    "template_level_tickets_id": "512600", 
    "ticket_id": "1559364"
  }, 
  {
    "catalog_id": "0", 
    "content_description_setting": "{\"product_title\":\"1\",\"image\":\"0\",\"guest_notification\":\"0\",\"cancellation_policy\":\"1\",\"short_desc\":\"0\",\"long_desc\":\"0\",\"highlights\":\"0\"}", 
    "created_at": "2024-12-23 11:54:22", 
    "deleted": "0", 
    "is_pos_list": "1", 
    "is_suspended": "0", 
    "last_modified_at": "2024-12-23 12:04:45", 
    "market_merchant_id": "1", 
    "merchant_admin_id": "148456", 
    "product_verify_status": "0", 
    "publish_catalog": "1", 
    "template_id": "17734", 
    "template_level_tickets_id": "512577", 
    "ticket_id": "1559454"
  }, 
  {
    "catalog_id": "0", 
    "content_description_setting": null, 
    "created_at": "2024-12-24 10:41:57", 
    "deleted": "0", 
    "is_pos_list": "1", 
    "is_suspended": "0", 
    "last_modified_at": "2024-12-24 10:41:57", 
    "market_merchant_id": "1", 
    "merchant_admin_id": "148964", 
    "product_verify_status": "0", 
    "publish_catalog": "1", 
    "template_id": "1170", 
    "template_level_tickets_id": "512596", 
    "ticket_id": "1559460"
  }, 
  {
    "catalog_id": "0", 
    "content_description_setting": "{\"product_title\":\"1\",\"image\":\"0\",\"guest_notification\":\"0\",\"cancellation_policy\":\"1\",\"short_desc\":\"0\",\"long_desc\":\"0\",\"highlights\":\"0\"}", 
    "created_at": "2024-12-31 06:45:39", 
    "deleted": "0", 
    "is_pos_list": "1", 
    "is_suspended": "0", 
    "last_modified_at": "2024-12-31 07:27:46", 
    "market_merchant_id": "1", 
    "merchant_admin_id": "149388", 
    "product_verify_status": "0", 
    "publish_catalog": "1", 
    "template_id": "19279", 
    "template_level_tickets_id": "512642", 
    "ticket_id": "1559508"
  }, 
  {
    "catalog_id": "0", 
    "content_description_setting": "{\"product_title\":\"1\",\"image\":\"0\",\"guest_notification\":\"0\",\"cancellation_policy\":\"1\",\"short_desc\":\"0\",\"long_desc\":\"0\",\"highlights\":\"0\"}", 
    "created_at": "2024-12-30 12:04:20", 
    "deleted": "0", 
    "is_pos_list": "1", 
    "is_suspended": "0", 
    "last_modified_at": "2024-12-30 12:08:01", 
    "market_merchant_id": "1", 
    "merchant_admin_id": "0", 
    "product_verify_status": "0", 
    "publish_catalog": "1", 
    "template_id": "19189", 
    "template_level_tickets_id": "512625", 
    "ticket_id": "1559492"
  }, 
  {
    "catalog_id": "0", 
    "content_description_setting": "{\"product_title\":\"1\",\"image\":\"0\",\"guest_notification\":\"0\",\"cancellation_policy\":\"1\",\"short_desc\":\"0\",\"long_desc\":\"0\",\"highlights\":\"0\"}", 
    "created_at": "2024-12-23 07:46:32", 
    "deleted": "0", 
    "is_pos_list": "1", 
    "is_suspended": "0", 
    "last_modified_at": "2024-12-23 07:48:29", 
    "market_merchant_id": "1", 
    "merchant_admin_id": "148456", 
    "product_verify_status": "0", 
    "publish_catalog": "1", 
    "template_id": "17734", 
    "template_level_tickets_id": "512574", 
    "ticket_id": "1559452"
  }, 
  {
    "catalog_id": "0", 
    "content_description_setting": "{\"product_title\":\"1\",\"image\":\"0\",\"guest_notification\":\"0\",\"cancellation_policy\":\"1\",\"short_desc\":\"0\",\"long_desc\":\"0\",\"highlights\":\"0\"}", 
    "created_at": "2024-12-24 10:20:34", 
    "deleted": "0", 
    "is_pos_list": "1", 
    "is_suspended": "0", 
    "last_modified_at": "2024-12-24 10:27:30", 
    "market_merchant_id": "1", 
    "merchant_admin_id": "0", 
    "product_verify_status": "0", 
    "publish_catalog": "1", 
    "template_id": "1900", 
    "template_level_tickets_id": "512594", 
    "ticket_id": "1559471"
  }, 
  {
    "catalog_id": "0", 
    "content_description_setting": "{\"product_title\":\"1\",\"image\":\"0\",\"guest_notification\":\"0\",\"cancellation_policy\":\"1\",\"short_desc\":\"0\",\"long_desc\":\"0\",\"highlights\":\"0\"}", 
    "created_at": "2024-12-25 08:27:11", 
    "deleted": "0", 
    "is_pos_list": "0", 
    "is_suspended": "0", 
    "last_modified_at": "2024-12-25 09:45:04", 
    "market_merchant_id": "1", 
    "merchant_admin_id": "0", 
    "product_verify_status": "0", 
    "publish_catalog": "1", 
    "template_id": "1349", 
    "template_level_tickets_id": "512607", 
    "ticket_id": "1559479"
  }, 
  {
    "catalog_id": "0", 
    "content_description_setting": "{\"product_title\":\"1\",\"image\":\"0\",\"guest_notification\":\"0\",\"cancellation_policy\":\"1\",\"short_desc\":\"0\",\"long_desc\":\"0\",\"highlights\":\"0\"}", 
    "created_at": "2024-12-23 06:14:24", 
    "deleted": "0", 
    "is_pos_list": "0", 
    "is_suspended": "0", 
    "last_modified_at": "2024-12-23 06:14:24", 
    "market_merchant_id": "1", 
    "merchant_admin_id": "0", 
    "product_verify_status": "0", 
    "publish_catalog": "1", 
    "template_id": "1342", 
    "template_level_tickets_id": "512570", 
    "ticket_id": "261120"
  }, 
  {
    "catalog_id": "0", 
    "content_description_setting": "{\"product_title\":\"1\",\"image\":\"0\",\"guest_notification\":\"0\",\"cancellation_policy\":\"1\",\"short_desc\":\"0\",\"long_desc\":\"0\",\"highlights\":\"0\"}", 
    "created_at": "2024-12-23 12:45:56", 
    "deleted": "0", 
    "is_pos_list": "1", 
    "is_suspended": "0", 
    "last_modified_at": "2024-12-23 12:46:43", 
    "market_merchant_id": "1", 
    "merchant_admin_id": "148456", 
    "product_verify_status": "0", 
    "publish_catalog": "1", 
    "template_id": "17734", 
    "template_level_tickets_id": "512580", 
    "ticket_id": "1559457"
  }, 
  {
    "catalog_id": "0", 
    "content_description_setting": "{\"product_title\":\"1\",\"image\":\"0\",\"guest_notification\":\"0\",\"cancellation_policy\":\"1\",\"short_desc\":\"0\",\"long_desc\":\"0\",\"highlights\":\"0\"}", 
    "created_at": "2024-12-24 04:41:15", 
    "deleted": "0", 
    "is_pos_list": "0", 
    "is_suspended": "0", 
    "last_modified_at": "2024-12-24 04:41:15", 
    "market_merchant_id": "1", 
    "merchant_admin_id": "0", 
    "product_verify_status": "0", 
    "publish_catalog": "0", 
    "template_id": "18413", 
    "template_level_tickets_id": "512583", 
    "ticket_id": "1559459"
  }, 
  {
    "catalog_id": "0", 
    "content_description_setting": "{\"product_title\":\"1\",\"image\":\"0\",\"guest_notification\":\"0\",\"cancellation_policy\":\"1\",\"short_desc\":\"0\",\"long_desc\":\"0\",\"highlights\":\"0\"}", 
    "created_at": "2024-12-30 05:09:38", 
    "deleted": "0", 
    "is_pos_list": "1", 
    "is_suspended": "0", 
    "last_modified_at": "2024-12-30 05:13:36", 
    "market_merchant_id": "1", 
    "merchant_admin_id": "0", 
    "product_verify_status": "0", 
    "publish_catalog": "1", 
    "template_id": "1170", 
    "template_level_tickets_id": "512619", 
    "ticket_id": "1559488"
  }, 
  {
    "catalog_id": "0", 
    "content_description_setting": "{\"product_title\":\"1\",\"image\":\"0\",\"guest_notification\":\"0\",\"cancellation_policy\":\"1\",\"short_desc\":\"0\",\"long_desc\":\"0\",\"highlights\":\"0\"}", 
    "created_at": "2024-12-31 07:03:42", 
    "deleted": "0", 
    "is_pos_list": "1", 
    "is_suspended": "0", 
    "last_modified_at": "2024-12-31 07:28:41", 
    "market_merchant_id": "1", 
    "merchant_admin_id": "149388", 
    "product_verify_status": "0", 
    "publish_catalog": "1", 
    "template_id": "19279", 
    "template_level_tickets_id": "512646", 
    "ticket_id": "1559511"
  }, 
  {
    "catalog_id": "0", 
    "content_description_setting": "{\"product_title\":\"1\",\"image\":\"0\",\"guest_notification\":\"0\",\"cancellation_policy\":\"1\",\"short_desc\":\"0\",\"long_desc\":\"0\",\"highlights\":\"0\"}", 
    "created_at": "2024-12-31 06:41:12", 
    "deleted": "0", 
    "is_pos_list": "1", 
    "is_suspended": "0", 
    "last_modified_at": "2024-12-31 07:28:09", 
    "market_merchant_id": "1", 
    "merchant_admin_id": "149388", 
    "product_verify_status": "0", 
    "publish_catalog": "1", 
    "template_id": "19279", 
    "template_level_tickets_id": "512641", 
    "ticket_id": "1559506"
  }, 
  {
    "catalog_id": "0", 
    "content_description_setting": "{\"product_title\":\"1\",\"image\":\"0\",\"guest_notification\":\"0\",\"cancellation_policy\":\"1\",\"short_desc\":\"0\",\"long_desc\":\"0\",\"highlights\":\"0\"}", 
    "created_at": "2024-12-24 07:44:56", 
    "deleted": "0", 
    "is_pos_list": "1", 
    "is_suspended": "0", 
    "last_modified_at": "2024-12-24 07:48:53", 
    "market_merchant_id": "1", 
    "merchant_admin_id": "149312", 
    "product_verify_status": "0", 
    "publish_catalog": "1", 
    "template_id": "19136", 
    "template_level_tickets_id": "512590", 
    "ticket_id": "1559465"
  }, 
  {
    "catalog_id": "0", 
    "content_description_setting": "{\"product_title\":\"1\",\"image\":\"0\",\"guest_notification\":\"0\",\"cancellation_policy\":\"1\",\"short_desc\":\"0\",\"long_desc\":\"0\",\"highlights\":\"0\"}", 
    "created_at": "2024-12-25 08:24:44", 
    "deleted": "0", 
    "is_pos_list": "1", 
    "is_suspended": "0", 
    "last_modified_at": "2024-12-25 09:45:22", 
    "market_merchant_id": "1", 
    "merchant_admin_id": "0", 
    "product_verify_status": "0", 
    "publish_catalog": "1", 
    "template_id": "1170", 
    "template_level_tickets_id": "512605", 
    "ticket_id": "1559480"
  }, 
  {
    "catalog_id": "0", 
    "content_description_setting": "{\"product_title\":\"1\",\"image\":\"0\",\"guest_notification\":\"0\",\"cancellation_policy\":\"1\",\"short_desc\":\"0\",\"long_desc\":\"0\",\"highlights\":\"0\"}", 
    "created_at": "2024-12-31 04:41:38", 
    "deleted": "0", 
    "is_pos_list": "1", 
    "is_suspended": "0", 
    "last_modified_at": "2024-12-31 04:44:14", 
    "market_merchant_id": "1", 
    "merchant_admin_id": "0", 
    "product_verify_status": "0", 
    "publish_catalog": "1", 
    "template_id": "19189", 
    "template_level_tickets_id": "512629", 
    "ticket_id": "1559495"
  }, 
  {
    "catalog_id": "0", 
    "content_description_setting": "{\"product_title\":\"1\",\"image\":\"0\",\"guest_notification\":\"0\",\"cancellation_policy\":\"1\",\"short_desc\":\"0\",\"long_desc\":\"0\",\"highlights\":\"0\"}", 
    "created_at": "2024-12-31 06:37:42", 
    "deleted": "0", 
    "is_pos_list": "1", 
    "is_suspended": "0", 
    "last_modified_at": "2024-12-31 07:27:53", 
    "market_merchant_id": "1", 
    "merchant_admin_id": "149388", 
    "product_verify_status": "0", 
    "publish_catalog": "1", 
    "template_id": "19279", 
    "template_level_tickets_id": "512639", 
    "ticket_id": "1559504"
  }
]
